pctk/__init__.py
pctk/config.py
pctk/multicellds.py
pctk/plot.py
pctk/povwriter.py
pctk/render.py
pctk/cmds/__init__.py
pctk/cmds/animate.py
pctk/cmds/pctk.py
pctk/cmds/summarize_simulation.py
pctk-0.2.3.dist-info/LICENSE
pctk-0.2.3.dist-info/METADATA
pctk-0.2.3.dist-info/WHEEL
pctk-0.2.3.dist-info/entry_points.txt
pctk-0.2.3.dist-info/top_level.txt
pctk-0.2.3.dist-info/RECORD
