Metadata-Version: 2.1
Name: pctk
Version: 0.2.3
Summary: PhysiCell ToolKit: a tool for handling MultiCellDS output from PhysiCell and PhysiBoSS simulations.
Author-email: Miguel Ponce de Leon <miguel.ponce@bsc.es>
License: BSD 3-Clause License
Project-URL: Homepage, https://github.com/migp11/pctk
Project-URL: Bug Tracker, https://github.com/migp11/pctk/issues
Classifier: Programming Language :: Python :: 3
Classifier: License :: OSI Approved :: MIT License
Classifier: Operating System :: OS Independent
Requires-Python: >=3.7
License-File: LICENSE
Requires-Dist: numpy
Requires-Dist: scipy
Requires-Dist: matplotlib
Requires-Dist: pandas
